<?xml version="1.0" ?>
<StrokeSet>
  <Stroke>
    <Point x="766" y="1267"/>
    <Point x="766" y="1267"/>
    <Point x="766" y="1267"/>
    <Point x="766" y="1267"/>
    <Point x="766" y="1267"/>
    <Point x="791" y="1275"/>
    <Point x="814" y="1290"/>
    <Point x="840" y="1316"/>
    <Point x="874" y="1344"/>
    <Point x="906" y="1388"/>
    <Point x="942" y="1436"/>
    <Point x="971" y="1495"/>
    <Point x="1001" y="1555"/>
    <Point x="1024" y="1623"/>
    <Point x="1045" y="1691"/>
    <Point x="1061" y="1753"/>
    <Point x="1079" y="1812"/>
    <Point x="1097" y="1858"/>
    <Point x="1117" y="1896"/>
    <Point x="1140" y="1919"/>
    <Point x="1164" y="1928"/>
    <Point x="1192" y="1923"/>
    <Point x="1220" y="1908"/>
    <Point x="1250" y="1879"/>
    <Point x="1284" y="1840"/>
    <Point x="1315" y="1793"/>
    <Point x="1349" y="1735"/>
    <Point x="1381" y="1671"/>
    <Point x="1417" y="1599"/>
    <Point x="1449" y="1525"/>
    <Point x="1483" y="1445"/>
    <Point x="1512" y="1374"/>
    <Point x="1536" y="1308"/>
    <Point x="1557" y="1252"/>
    <Point x="1571" y="1213"/>
    <Point x="1586" y="1185"/>
    <Point x="1586" y="1185"/>
    <Point x="1586" y="1185"/>
    <Point x="1586" y="1185"/>
    <Point x="1563" y="1224"/>
  </Stroke>
  <Stroke>
    <Point x="788" y="1305"/>
    <Point x="784" y="1332"/>
    <Point x="788" y="1346"/>
    <Point x="796" y="1376"/>
    <Point x="805" y="1415"/>
    <Point x="817" y="1463"/>
    <Point x="834" y="1518"/>
    <Point x="853" y="1581"/>
    <Point x="873" y="1649"/>
    <Point x="897" y="1718"/>
    <Point x="921" y="1784"/>
    <Point x="947" y="1842"/>
    <Point x="966" y="1887"/>
    <Point x="989" y="1922"/>
    <Point x="1005" y="1943"/>
    <Point x="1025" y="1946"/>
    <Point x="1042" y="1932"/>
    <Point x="1060" y="1902"/>
    <Point x="1076" y="1861"/>
    <Point x="1097" y="1809"/>
    <Point x="1120" y="1744"/>
    <Point x="1146" y="1668"/>
    <Point x="1173" y="1593"/>
    <Point x="1201" y="1516"/>
    <Point x="1227" y="1442"/>
    <Point x="1250" y="1381"/>
    <Point x="1274" y="1329"/>
    <Point x="1293" y="1295"/>
    <Point x="1293" y="1295"/>
    <Point x="1316" y="1275"/>
    <Point x="1318" y="1292"/>
  </Stroke>
</StrokeSet>
