<?xml version="1.0" ?>
<StrokeSet>
  <Stroke>
    <Point x="392" y="1478"/>
    <Point x="392" y="1478"/>
    <Point x="392" y="1478"/>
    <Point x="392" y="1478"/>
    <Point x="393" y="1492"/>
    <Point x="396" y="1507"/>
    <Point x="399" y="1525"/>
    <Point x="406" y="1548"/>
    <Point x="410" y="1579"/>
    <Point x="419" y="1614"/>
    <Point x="425" y="1658"/>
    <Point x="440" y="1699"/>
    <Point x="448" y="1748"/>
    <Point x="463" y="1787"/>
    <Point x="475" y="1831"/>
    <Point x="490" y="1866"/>
    <Point x="502" y="1897"/>
    <Point x="531" y="1913"/>
    <Point x="546" y="1931"/>
    <Point x="579" y="1922"/>
    <Point x="603" y="1916"/>
    <Point x="644" y="1888"/>
    <Point x="677" y="1861"/>
    <Point x="724" y="1813"/>
    <Point x="766" y="1766"/>
    <Point x="807" y="1708"/>
    <Point x="847" y="1646"/>
    <Point x="882" y="1589"/>
    <Point x="911" y="1534"/>
    <Point x="935" y="1488"/>
    <Point x="950" y="1447"/>
    <Point x="960" y="1412"/>
    <Point x="962" y="1390"/>
    <Point x="960" y="1373"/>
    <Point x="947" y="1367"/>
    <Point x="924" y="1368"/>
    <Point x="901" y="1371"/>
    <Point x="871" y="1381"/>
  </Stroke>
  <Stroke>
    <Point x="656" y="1491"/>
    <Point x="656" y="1491"/>
    <Point x="645" y="1509"/>
    <Point x="645" y="1509"/>
    <Point x="662" y="1527"/>
    <Point x="666" y="1554"/>
    <Point x="696" y="1575"/>
    <Point x="713" y="1622"/>
    <Point x="749" y="1656"/>
    <Point x="775" y="1708"/>
    <Point x="813" y="1745"/>
    <Point x="844" y="1793"/>
    <Point x="880" y="1827"/>
    <Point x="915" y="1861"/>
    <Point x="944" y="1882"/>
    <Point x="972" y="1893"/>
    <Point x="998" y="1897"/>
    <Point x="1027" y="1890"/>
    <Point x="1055" y="1873"/>
    <Point x="1085" y="1846"/>
    <Point x="1119" y="1809"/>
    <Point x="1153" y="1760"/>
    <Point x="1192" y="1705"/>
    <Point x="1236" y="1641"/>
    <Point x="1278" y="1578"/>
    <Point x="1324" y="1518"/>
    <Point x="1366" y="1460"/>
    <Point x="1400" y="1412"/>
    <Point x="1437" y="1368"/>
    <Point x="1462" y="1344"/>
    <Point x="1480" y="1319"/>
    <Point x="1497" y="1298"/>
    <Point x="1503" y="1284"/>
    <Point x="1501" y="1263"/>
  </Stroke>
  <Stroke>
    <Point x="598" y="1474"/>
    <Point x="597" y="1460"/>
    <Point x="597" y="1460"/>
    <Point x="597" y="1460"/>
    <Point x="601" y="1486"/>
    <Point x="603" y="1516"/>
    <Point x="615" y="1546"/>
    <Point x="618" y="1590"/>
    <Point x="633" y="1632"/>
    <Point x="639" y="1685"/>
    <Point x="651" y="1730"/>
    <Point x="659" y="1780"/>
    <Point x="675" y="1818"/>
    <Point x="687" y="1851"/>
    <Point x="707" y="1870"/>
    <Point x="727" y="1882"/>
    <Point x="752" y="1878"/>
    <Point x="782" y="1864"/>
    <Point x="816" y="1840"/>
    <Point x="850" y="1810"/>
    <Point x="888" y="1769"/>
    <Point x="924" y="1721"/>
    <Point x="959" y="1673"/>
    <Point x="989" y="1625"/>
    <Point x="1016" y="1581"/>
    <Point x="1042" y="1545"/>
    <Point x="1055" y="1516"/>
    <Point x="1075" y="1492"/>
    <Point x="1076" y="1478"/>
    <Point x="1076" y="1478"/>
    <Point x="1070" y="1460"/>
    <Point x="1070" y="1460"/>
    <Point x="1045" y="1459"/>
  </Stroke>
  <Stroke>
    <Point x="885" y="1513"/>
    <Point x="879" y="1530"/>
    <Point x="879" y="1530"/>
    <Point x="898" y="1536"/>
    <Point x="904" y="1549"/>
    <Point x="926" y="1560"/>
    <Point x="938" y="1593"/>
    <Point x="963" y="1617"/>
    <Point x="983" y="1659"/>
    <Point x="1009" y="1694"/>
    <Point x="1033" y="1741"/>
    <Point x="1061" y="1781"/>
    <Point x="1085" y="1824"/>
    <Point x="1116" y="1854"/>
    <Point x="1143" y="1879"/>
    <Point x="1174" y="1890"/>
    <Point x="1209" y="1888"/>
    <Point x="1245" y="1875"/>
    <Point x="1278" y="1851"/>
    <Point x="1316" y="1815"/>
    <Point x="1357" y="1771"/>
    <Point x="1402" y="1720"/>
    <Point x="1447" y="1659"/>
    <Point x="1447" y="1659"/>
    <Point x="1536" y="1549"/>
    <Point x="1536" y="1549"/>
    <Point x="1621" y="1463"/>
    <Point x="1621" y="1463"/>
    <Point x="1681" y="1412"/>
    <Point x="1681" y="1412"/>
    <Point x="1681" y="1412"/>
  </Stroke>
</StrokeSet>
