<?xml version="1.0" ?>
<StrokeSet>
  <Stroke>
    <Point x="683" y="447"/>
    <Point x="683" y="447"/>
    <Point x="683" y="447"/>
    <Point x="683" y="447"/>
    <Point x="683" y="447"/>
    <Point x="688" y="438"/>
    <Point x="688" y="438"/>
    <Point x="688" y="438"/>
    <Point x="688" y="438"/>
    <Point x="688" y="438"/>
    <Point x="688" y="438"/>
    <Point x="688" y="438"/>
    <Point x="688" y="438"/>
    <Point x="676" y="440"/>
    <Point x="676" y="440"/>
    <Point x="665" y="444"/>
    <Point x="656" y="447"/>
    <Point x="656" y="447"/>
    <Point x="637" y="454"/>
    <Point x="637" y="454"/>
    <Point x="618" y="472"/>
    <Point x="618" y="472"/>
    <Point x="603" y="495"/>
    <Point x="601" y="509"/>
    <Point x="598" y="525"/>
    <Point x="601" y="542"/>
    <Point x="604" y="558"/>
    <Point x="612" y="566"/>
    <Point x="624" y="580"/>
    <Point x="638" y="590"/>
    <Point x="654" y="594"/>
    <Point x="672" y="594"/>
    <Point x="688" y="589"/>
    <Point x="704" y="580"/>
    <Point x="717" y="564"/>
    <Point x="726" y="547"/>
    <Point x="731" y="524"/>
    <Point x="732" y="499"/>
    <Point x="726" y="477"/>
    <Point x="715" y="457"/>
    <Point x="699" y="440"/>
    <Point x="680" y="430"/>
    <Point x="661" y="428"/>
    <Point x="641" y="430"/>
    <Point x="626" y="442"/>
    <Point x="609" y="463"/>
    <Point x="601" y="486"/>
    <Point x="602" y="513"/>
    <Point x="610" y="535"/>
    <Point x="625" y="549"/>
  </Stroke>
  <Stroke>
    <Point x="434" y="375"/>
    <Point x="434" y="366"/>
    <Point x="434" y="366"/>
    <Point x="420" y="361"/>
    <Point x="420" y="361"/>
    <Point x="402" y="363"/>
    <Point x="402" y="363"/>
    <Point x="384" y="375"/>
    <Point x="380" y="384"/>
    <Point x="372" y="402"/>
    <Point x="371" y="419"/>
    <Point x="372" y="441"/>
    <Point x="380" y="459"/>
    <Point x="389" y="477"/>
    <Point x="403" y="492"/>
    <Point x="418" y="502"/>
    <Point x="436" y="502"/>
    <Point x="453" y="501"/>
    <Point x="471" y="486"/>
    <Point x="485" y="467"/>
    <Point x="498" y="445"/>
    <Point x="506" y="421"/>
    <Point x="510" y="393"/>
    <Point x="512" y="364"/>
    <Point x="504" y="336"/>
    <Point x="499" y="309"/>
    <Point x="488" y="290"/>
    <Point x="473" y="276"/>
    <Point x="455" y="271"/>
    <Point x="439" y="269"/>
    <Point x="421" y="279"/>
    <Point x="407" y="293"/>
    <Point x="395" y="314"/>
    <Point x="389" y="334"/>
    <Point x="382" y="360"/>
    <Point x="386" y="384"/>
    <Point x="399" y="402"/>
    <Point x="412" y="420"/>
    <Point x="438" y="425"/>
  </Stroke>
  <Stroke>
    <Point x="340" y="589"/>
    <Point x="323" y="589"/>
    <Point x="314" y="591"/>
    <Point x="314" y="591"/>
    <Point x="297" y="591"/>
    <Point x="297" y="591"/>
    <Point x="284" y="586"/>
    <Point x="284" y="586"/>
    <Point x="271" y="588"/>
    <Point x="271" y="588"/>
    <Point x="260" y="591"/>
    <Point x="260" y="591"/>
    <Point x="260" y="591"/>
    <Point x="260" y="591"/>
    <Point x="260" y="591"/>
    <Point x="277" y="591"/>
    <Point x="295" y="591"/>
    <Point x="320" y="591"/>
    <Point x="350" y="594"/>
    <Point x="385" y="594"/>
    <Point x="420" y="597"/>
    <Point x="457" y="597"/>
    <Point x="491" y="602"/>
    <Point x="522" y="605"/>
    <Point x="550" y="606"/>
    <Point x="570" y="608"/>
    <Point x="593" y="603"/>
    <Point x="604" y="599"/>
    <Point x="604" y="599"/>
    <Point x="604" y="584"/>
    <Point x="598" y="570"/>
  </Stroke>
</StrokeSet>
