<?xml version="1.0" ?>
<StrokeSet>
  <Stroke>
    <Point x="724" y="2362"/>
    <Point x="724" y="2362"/>
    <Point x="739" y="2368"/>
    <Point x="739" y="2368"/>
    <Point x="763" y="2350"/>
    <Point x="781" y="2335"/>
    <Point x="803" y="2312"/>
    <Point x="829" y="2289"/>
    <Point x="861" y="2259"/>
    <Point x="889" y="2229"/>
    <Point x="920" y="2194"/>
    <Point x="947" y="2166"/>
    <Point x="968" y="2136"/>
    <Point x="983" y="2114"/>
    <Point x="995" y="2096"/>
    <Point x="1002" y="2083"/>
    <Point x="1002" y="2083"/>
    <Point x="1007" y="2063"/>
    <Point x="1007" y="2063"/>
    <Point x="1012" y="2045"/>
    <Point x="1022" y="2030"/>
    <Point x="1022" y="2030"/>
    <Point x="1039" y="1991"/>
  </Stroke>
  <Stroke>
    <Point x="1165" y="1596"/>
    <Point x="1165" y="1596"/>
    <Point x="1165" y="1596"/>
    <Point x="1165" y="1596"/>
    <Point x="1165" y="1596"/>
    <Point x="1165" y="1596"/>
    <Point x="1165" y="1596"/>
    <Point x="1165" y="1596"/>
    <Point x="1165" y="1596"/>
    <Point x="1165" y="1596"/>
    <Point x="1165" y="1596"/>
    <Point x="1165" y="1596"/>
    <Point x="1165" y="1596"/>
    <Point x="1165" y="1596"/>
  </Stroke>
  <Stroke>
    <Point x="787" y="1447"/>
    <Point x="770" y="1450"/>
    <Point x="770" y="1450"/>
    <Point x="745" y="1474"/>
    <Point x="718" y="1498"/>
    <Point x="696" y="1521"/>
    <Point x="662" y="1555"/>
    <Point x="636" y="1587"/>
    <Point x="605" y="1622"/>
    <Point x="582" y="1650"/>
    <Point x="558" y="1679"/>
    <Point x="541" y="1700"/>
    <Point x="529" y="1717"/>
    <Point x="516" y="1733"/>
    <Point x="516" y="1733"/>
    <Point x="516" y="1733"/>
    <Point x="516" y="1733"/>
    <Point x="513" y="1718"/>
  </Stroke>
  <Stroke>
    <Point x="908" y="1055"/>
    <Point x="906" y="1075"/>
    <Point x="906" y="1075"/>
    <Point x="906" y="1075"/>
    <Point x="906" y="1075"/>
    <Point x="906" y="1075"/>
    <Point x="906" y="1075"/>
    <Point x="906" y="1075"/>
    <Point x="906" y="1075"/>
    <Point x="906" y="1075"/>
    <Point x="906" y="1075"/>
    <Point x="906" y="1075"/>
    <Point x="921" y="1070"/>
    <Point x="921" y="1070"/>
    <Point x="921" y="1070"/>
    <Point x="908" y="1050"/>
    <Point x="908" y="1050"/>
  </Stroke>
</StrokeSet>
