<?xml version="1.0" ?>
<StrokeSet>
  <Stroke>
    <Point x="819" y="1354"/>
    <Point x="788" y="1359"/>
    <Point x="770" y="1360"/>
    <Point x="737" y="1378"/>
    <Point x="710" y="1396"/>
    <Point x="686" y="1422"/>
    <Point x="656" y="1455"/>
    <Point x="639" y="1491"/>
    <Point x="621" y="1541"/>
    <Point x="620" y="1589"/>
    <Point x="623" y="1645"/>
    <Point x="644" y="1695"/>
    <Point x="671" y="1746"/>
    <Point x="713" y="1787"/>
    <Point x="763" y="1823"/>
    <Point x="820" y="1846"/>
    <Point x="879" y="1859"/>
    <Point x="941" y="1861"/>
    <Point x="998" y="1850"/>
    <Point x="1054" y="1828"/>
    <Point x="1100" y="1796"/>
    <Point x="1140" y="1752"/>
    <Point x="1167" y="1701"/>
    <Point x="1182" y="1644"/>
    <Point x="1182" y="1588"/>
    <Point x="1168" y="1533"/>
    <Point x="1135" y="1487"/>
    <Point x="1085" y="1446"/>
    <Point x="1018" y="1417"/>
    <Point x="939" y="1399"/>
    <Point x="859" y="1393"/>
    <Point x="775" y="1398"/>
    <Point x="706" y="1398"/>
    <Point x="653" y="1402"/>
    <Point x="617" y="1410"/>
    <Point x="617" y="1410"/>
  </Stroke>
  <Stroke>
    <Point x="1039" y="777"/>
    <Point x="1039" y="777"/>
    <Point x="1039" y="777"/>
    <Point x="1039" y="777"/>
    <Point x="1018" y="790"/>
    <Point x="999" y="811"/>
    <Point x="977" y="846"/>
    <Point x="957" y="890"/>
    <Point x="929" y="942"/>
    <Point x="912" y="988"/>
    <Point x="889" y="1042"/>
  </Stroke>
  <Stroke>
    <Point x="793" y="1432"/>
    <Point x="793" y="1432"/>
    <Point x="793" y="1432"/>
    <Point x="776" y="1428"/>
    <Point x="763" y="1423"/>
    <Point x="743" y="1432"/>
    <Point x="722" y="1446"/>
    <Point x="701" y="1467"/>
    <Point x="675" y="1497"/>
    <Point x="659" y="1532"/>
    <Point x="642" y="1574"/>
    <Point x="642" y="1615"/>
    <Point x="644" y="1663"/>
    <Point x="666" y="1704"/>
    <Point x="690" y="1749"/>
    <Point x="733" y="1781"/>
    <Point x="778" y="1808"/>
    <Point x="832" y="1820"/>
    <Point x="888" y="1823"/>
    <Point x="945" y="1811"/>
    <Point x="999" y="1791"/>
    <Point x="1049" y="1757"/>
    <Point x="1091" y="1714"/>
    <Point x="1125" y="1666"/>
    <Point x="1144" y="1612"/>
    <Point x="1150" y="1555"/>
    <Point x="1140" y="1500"/>
    <Point x="1117" y="1451"/>
    <Point x="1079" y="1411"/>
    <Point x="1030" y="1384"/>
    <Point x="966" y="1368"/>
    <Point x="895" y="1363"/>
    <Point x="832" y="1369"/>
    <Point x="770" y="1389"/>
    <Point x="722" y="1411"/>
    <Point x="693" y="1426"/>
    <Point x="680" y="1443"/>
    <Point x="680" y="1443"/>
  </Stroke>
  <Stroke>
    <Point x="1058" y="1081"/>
    <Point x="1076" y="1052"/>
    <Point x="1082" y="1039"/>
    <Point x="1099" y="1018"/>
    <Point x="1113" y="998"/>
    <Point x="1125" y="985"/>
    <Point x="1137" y="971"/>
    <Point x="1144" y="957"/>
    <Point x="1162" y="941"/>
    <Point x="1162" y="941"/>
    <Point x="1176" y="926"/>
  </Stroke>
</StrokeSet>
