<?xml version="1.0" ?>
<StrokeSet>
  <Stroke>
    <Point x="502" y="1539"/>
    <Point x="482" y="1540"/>
    <Point x="482" y="1540"/>
    <Point x="482" y="1540"/>
    <Point x="482" y="1540"/>
    <Point x="504" y="1548"/>
    <Point x="529" y="1548"/>
    <Point x="559" y="1539"/>
    <Point x="595" y="1525"/>
    <Point x="638" y="1509"/>
    <Point x="684" y="1481"/>
    <Point x="734" y="1442"/>
    <Point x="782" y="1405"/>
    <Point x="831" y="1352"/>
    <Point x="879" y="1302"/>
    <Point x="926" y="1243"/>
    <Point x="969" y="1188"/>
    <Point x="1009" y="1120"/>
    <Point x="1043" y="1058"/>
    <Point x="1075" y="993"/>
    <Point x="1097" y="933"/>
    <Point x="1116" y="870"/>
    <Point x="1125" y="806"/>
    <Point x="1125" y="806"/>
    <Point x="1122" y="708"/>
    <Point x="1122" y="708"/>
    <Point x="1096" y="627"/>
    <Point x="1096" y="627"/>
    <Point x="1096" y="627"/>
    <Point x="1034" y="574"/>
    <Point x="1034" y="574"/>
    <Point x="1034" y="574"/>
    <Point x="1034" y="574"/>
    <Point x="966" y="645"/>
    <Point x="966" y="645"/>
    <Point x="938" y="735"/>
    <Point x="926" y="793"/>
    <Point x="912" y="864"/>
    <Point x="900" y="942"/>
    <Point x="891" y="1031"/>
    <Point x="880" y="1126"/>
    <Point x="873" y="1231"/>
    <Point x="870" y="1346"/>
    <Point x="871" y="1471"/>
    <Point x="873" y="1599"/>
    <Point x="877" y="1727"/>
    <Point x="883" y="1852"/>
    <Point x="889" y="1977"/>
    <Point x="892" y="2096"/>
    <Point x="891" y="2206"/>
    <Point x="882" y="2309"/>
    <Point x="867" y="2401"/>
    <Point x="844" y="2476"/>
    <Point x="819" y="2538"/>
    <Point x="785" y="2585"/>
    <Point x="746" y="2615"/>
    <Point x="707" y="2630"/>
    <Point x="668" y="2630"/>
    <Point x="632" y="2615"/>
    <Point x="597" y="2582"/>
    <Point x="568" y="2544"/>
    <Point x="546" y="2496"/>
    <Point x="529" y="2437"/>
    <Point x="523" y="2377"/>
    <Point x="529" y="2315"/>
    <Point x="540" y="2256"/>
    <Point x="559" y="2199"/>
    <Point x="588" y="2142"/>
    <Point x="620" y="2083"/>
    <Point x="656" y="2033"/>
    <Point x="696" y="1998"/>
    <Point x="737" y="1961"/>
    <Point x="776" y="1934"/>
    <Point x="817" y="1914"/>
    <Point x="862" y="1897"/>
    <Point x="906" y="1894"/>
    <Point x="942" y="1890"/>
    <Point x="986" y="1876"/>
    <Point x="1010" y="1866"/>
  </Stroke>
  <Stroke>
    <Point x="621" y="1477"/>
    <Point x="630" y="1491"/>
    <Point x="647" y="1485"/>
    <Point x="647" y="1485"/>
    <Point x="675" y="1474"/>
    <Point x="695" y="1463"/>
    <Point x="719" y="1444"/>
    <Point x="746" y="1417"/>
    <Point x="775" y="1388"/>
    <Point x="807" y="1347"/>
    <Point x="831" y="1307"/>
    <Point x="852" y="1257"/>
    <Point x="862" y="1213"/>
    <Point x="871" y="1160"/>
    <Point x="868" y="1115"/>
    <Point x="864" y="1066"/>
    <Point x="850" y="1029"/>
    <Point x="838" y="995"/>
    <Point x="820" y="975"/>
    <Point x="805" y="966"/>
    <Point x="788" y="969"/>
    <Point x="776" y="984"/>
    <Point x="766" y="1017"/>
    <Point x="757" y="1061"/>
    <Point x="749" y="1120"/>
    <Point x="740" y="1192"/>
    <Point x="734" y="1278"/>
    <Point x="733" y="1381"/>
    <Point x="733" y="1495"/>
    <Point x="736" y="1622"/>
    <Point x="743" y="1748"/>
    <Point x="752" y="1879"/>
    <Point x="764" y="1997"/>
    <Point x="776" y="2111"/>
    <Point x="790" y="2208"/>
    <Point x="802" y="2288"/>
    <Point x="810" y="2348"/>
    <Point x="813" y="2390"/>
    <Point x="807" y="2414"/>
    <Point x="807" y="2414"/>
    <Point x="778" y="2414"/>
    <Point x="761" y="2389"/>
    <Point x="740" y="2353"/>
    <Point x="722" y="2300"/>
    <Point x="709" y="2238"/>
    <Point x="702" y="2167"/>
    <Point x="707" y="2089"/>
    <Point x="725" y="2004"/>
    <Point x="752" y="1928"/>
    <Point x="788" y="1854"/>
    <Point x="831" y="1790"/>
    <Point x="876" y="1735"/>
    <Point x="921" y="1689"/>
    <Point x="963" y="1655"/>
    <Point x="1004" y="1632"/>
    <Point x="1039" y="1610"/>
    <Point x="1061" y="1604"/>
    <Point x="1081" y="1592"/>
    <Point x="1081" y="1592"/>
  </Stroke>
</StrokeSet>
