<?xml version="1.0" ?>
<StrokeSet>
  <Stroke>
    <Point x="976" y="1509"/>
    <Point x="976" y="1509"/>
    <Point x="976" y="1509"/>
    <Point x="959" y="1505"/>
    <Point x="959" y="1505"/>
  </Stroke>
  <Stroke>
    <Point x="1029" y="1820"/>
    <Point x="1029" y="1820"/>
    <Point x="1014" y="1831"/>
    <Point x="1014" y="1831"/>
    <Point x="1005" y="1852"/>
    <Point x="1002" y="1865"/>
    <Point x="997" y="1886"/>
    <Point x="991" y="1912"/>
    <Point x="984" y="1939"/>
    <Point x="976" y="1971"/>
    <Point x="965" y="2001"/>
    <Point x="956" y="2034"/>
    <Point x="943" y="2066"/>
    <Point x="934" y="2099"/>
    <Point x="923" y="2131"/>
    <Point x="917" y="2159"/>
    <Point x="913" y="2183"/>
    <Point x="907" y="2207"/>
    <Point x="907" y="2207"/>
    <Point x="913" y="2233"/>
  </Stroke>
  <Stroke>
    <Point x="966" y="1421"/>
    <Point x="951" y="1418"/>
    <Point x="951" y="1418"/>
    <Point x="951" y="1418"/>
    <Point x="951" y="1418"/>
    <Point x="951" y="1418"/>
    <Point x="951" y="1418"/>
    <Point x="951" y="1418"/>
    <Point x="951" y="1418"/>
    <Point x="968" y="1414"/>
    <Point x="968" y="1414"/>
    <Point x="981" y="1412"/>
    <Point x="981" y="1412"/>
    <Point x="981" y="1412"/>
    <Point x="992" y="1397"/>
    <Point x="992" y="1397"/>
    <Point x="992" y="1397"/>
    <Point x="983" y="1381"/>
    <Point x="983" y="1381"/>
    <Point x="969" y="1373"/>
    <Point x="969" y="1373"/>
    <Point x="969" y="1373"/>
    <Point x="954" y="1371"/>
    <Point x="954" y="1371"/>
    <Point x="953" y="1385"/>
    <Point x="966" y="1378"/>
    <Point x="966" y="1378"/>
  </Stroke>
  <Stroke>
    <Point x="996" y="1620"/>
    <Point x="996" y="1620"/>
    <Point x="996" y="1620"/>
    <Point x="996" y="1620"/>
    <Point x="993" y="1640"/>
    <Point x="993" y="1640"/>
    <Point x="996" y="1658"/>
    <Point x="996" y="1658"/>
    <Point x="999" y="1685"/>
    <Point x="1001" y="1702"/>
    <Point x="1002" y="1721"/>
    <Point x="999" y="1744"/>
    <Point x="996" y="1769"/>
    <Point x="989" y="1800"/>
    <Point x="980" y="1831"/>
    <Point x="969" y="1866"/>
    <Point x="956" y="1897"/>
    <Point x="941" y="1932"/>
    <Point x="927" y="1962"/>
    <Point x="914" y="1989"/>
    <Point x="903" y="2012"/>
    <Point x="891" y="2033"/>
    <Point x="891" y="2033"/>
    <Point x="871" y="2057"/>
    <Point x="871" y="2057"/>
    <Point x="855" y="2068"/>
    <Point x="855" y="2068"/>
    <Point x="838" y="2072"/>
    <Point x="838" y="2072"/>
    <Point x="823" y="2072"/>
    <Point x="823" y="2072"/>
    <Point x="810" y="2072"/>
    <Point x="810" y="2072"/>
    <Point x="810" y="2072"/>
    <Point x="810" y="2072"/>
    <Point x="810" y="2072"/>
    <Point x="810" y="2072"/>
    <Point x="810" y="2072"/>
    <Point x="828" y="2072"/>
    <Point x="828" y="2072"/>
  </Stroke>
</StrokeSet>
