<?xml version="1.0" ?>
<StrokeSet>
  <Stroke>
    <Point x="288" y="513"/>
    <Point x="288" y="513"/>
    <Point x="268" y="461"/>
    <Point x="268" y="461"/>
    <Point x="268" y="461"/>
    <Point x="268" y="461"/>
    <Point x="260" y="413"/>
    <Point x="260" y="413"/>
    <Point x="260" y="413"/>
    <Point x="260" y="413"/>
    <Point x="260" y="413"/>
    <Point x="260" y="413"/>
    <Point x="260" y="413"/>
    <Point x="260" y="413"/>
    <Point x="272" y="476"/>
    <Point x="272" y="476"/>
    <Point x="285" y="558"/>
    <Point x="292" y="606"/>
    <Point x="302" y="662"/>
    <Point x="315" y="724"/>
    <Point x="327" y="791"/>
    <Point x="341" y="861"/>
    <Point x="353" y="936"/>
    <Point x="367" y="1010"/>
    <Point x="378" y="1080"/>
    <Point x="390" y="1145"/>
    <Point x="401" y="1202"/>
    <Point x="412" y="1247"/>
    <Point x="412" y="1247"/>
    <Point x="412" y="1247"/>
    <Point x="412" y="1247"/>
    <Point x="465" y="1256"/>
    <Point x="483" y="1215"/>
    <Point x="505" y="1166"/>
    <Point x="527" y="1106"/>
    <Point x="552" y="1039"/>
    <Point x="577" y="973"/>
    <Point x="604" y="907"/>
    <Point x="628" y="846"/>
    <Point x="651" y="794"/>
    <Point x="672" y="745"/>
    <Point x="672" y="745"/>
    <Point x="706" y="674"/>
    <Point x="706" y="674"/>
    <Point x="732" y="622"/>
    <Point x="732" y="622"/>
  </Stroke>
  <Stroke>
    <Point x="290" y="419"/>
    <Point x="290" y="419"/>
    <Point x="290" y="419"/>
    <Point x="287" y="377"/>
    <Point x="287" y="377"/>
    <Point x="287" y="377"/>
    <Point x="287" y="377"/>
    <Point x="287" y="377"/>
    <Point x="287" y="377"/>
    <Point x="287" y="377"/>
    <Point x="287" y="377"/>
    <Point x="321" y="416"/>
    <Point x="321" y="416"/>
    <Point x="337" y="492"/>
    <Point x="346" y="542"/>
    <Point x="355" y="605"/>
    <Point x="363" y="673"/>
    <Point x="369" y="751"/>
    <Point x="377" y="833"/>
    <Point x="384" y="918"/>
    <Point x="392" y="1002"/>
    <Point x="399" y="1083"/>
    <Point x="405" y="1158"/>
    <Point x="413" y="1223"/>
    <Point x="421" y="1275"/>
    <Point x="421" y="1275"/>
    <Point x="440" y="1326"/>
    <Point x="440" y="1326"/>
    <Point x="440" y="1326"/>
    <Point x="488" y="1241"/>
    <Point x="514" y="1178"/>
    <Point x="540" y="1101"/>
    <Point x="570" y="1019"/>
    <Point x="600" y="929"/>
    <Point x="631" y="843"/>
    <Point x="659" y="765"/>
    <Point x="685" y="699"/>
    <Point x="707" y="642"/>
    <Point x="725" y="597"/>
    <Point x="725" y="597"/>
    <Point x="746" y="541"/>
  </Stroke>
</StrokeSet>
