<?xml version="1.0" ?>
<StrokeSet>
  <Stroke>
    <Point x="505" y="709"/>
    <Point x="491" y="692"/>
    <Point x="476" y="686"/>
    <Point x="463" y="669"/>
    <Point x="455" y="656"/>
    <Point x="441" y="652"/>
    <Point x="442" y="642"/>
    <Point x="442" y="642"/>
    <Point x="442" y="642"/>
    <Point x="465" y="648"/>
    <Point x="491" y="654"/>
    <Point x="524" y="666"/>
    <Point x="566" y="682"/>
    <Point x="613" y="703"/>
    <Point x="664" y="726"/>
    <Point x="717" y="754"/>
    <Point x="767" y="782"/>
    <Point x="812" y="811"/>
    <Point x="848" y="840"/>
    <Point x="875" y="873"/>
    <Point x="893" y="899"/>
    <Point x="895" y="922"/>
    <Point x="885" y="943"/>
    <Point x="862" y="960"/>
    <Point x="823" y="978"/>
    <Point x="772" y="992"/>
    <Point x="710" y="1009"/>
    <Point x="641" y="1023"/>
    <Point x="570" y="1032"/>
    <Point x="500" y="1045"/>
    <Point x="440" y="1056"/>
    <Point x="393" y="1066"/>
    <Point x="360" y="1082"/>
    <Point x="352" y="1091"/>
    <Point x="365" y="1092"/>
    <Point x="392" y="1080"/>
    <Point x="438" y="1068"/>
  </Stroke>
  <Stroke>
    <Point x="299" y="739"/>
    <Point x="281" y="729"/>
    <Point x="261" y="724"/>
    <Point x="241" y="713"/>
    <Point x="232" y="707"/>
    <Point x="219" y="711"/>
    <Point x="219" y="711"/>
    <Point x="219" y="711"/>
    <Point x="243" y="709"/>
    <Point x="264" y="718"/>
    <Point x="297" y="727"/>
    <Point x="336" y="741"/>
    <Point x="382" y="754"/>
    <Point x="431" y="767"/>
    <Point x="483" y="781"/>
    <Point x="535" y="795"/>
    <Point x="583" y="811"/>
    <Point x="627" y="826"/>
    <Point x="663" y="836"/>
    <Point x="689" y="850"/>
    <Point x="708" y="863"/>
    <Point x="708" y="863"/>
    <Point x="710" y="889"/>
    <Point x="691" y="899"/>
    <Point x="661" y="912"/>
    <Point x="620" y="927"/>
    <Point x="570" y="940"/>
    <Point x="515" y="955"/>
    <Point x="456" y="968"/>
    <Point x="400" y="986"/>
    <Point x="351" y="1001"/>
    <Point x="314" y="1013"/>
    <Point x="287" y="1025"/>
    <Point x="287" y="1025"/>
    <Point x="295" y="1037"/>
    <Point x="320" y="1037"/>
    <Point x="354" y="1033"/>
    <Point x="395" y="1016"/>
  </Stroke>
</StrokeSet>
