<?xml version="1.0" ?>
<StrokeSet>
  <Stroke>
    <Point x="544" y="1017"/>
    <Point x="544" y="1017"/>
    <Point x="578" y="969"/>
    <Point x="578" y="969"/>
    <Point x="578" y="969"/>
    <Point x="596" y="921"/>
    <Point x="596" y="921"/>
    <Point x="596" y="921"/>
    <Point x="601" y="879"/>
    <Point x="601" y="879"/>
    <Point x="601" y="879"/>
    <Point x="560" y="850"/>
    <Point x="560" y="850"/>
    <Point x="503" y="844"/>
    <Point x="503" y="844"/>
    <Point x="424" y="860"/>
    <Point x="382" y="879"/>
    <Point x="342" y="909"/>
    <Point x="342" y="909"/>
    <Point x="275" y="975"/>
    <Point x="258" y="1022"/>
    <Point x="251" y="1071"/>
    <Point x="256" y="1117"/>
    <Point x="270" y="1158"/>
    <Point x="270" y="1158"/>
    <Point x="327" y="1216"/>
    <Point x="327" y="1216"/>
    <Point x="404" y="1241"/>
    <Point x="404" y="1241"/>
    <Point x="477" y="1214"/>
    <Point x="477" y="1214"/>
    <Point x="540" y="1159"/>
    <Point x="540" y="1159"/>
    <Point x="581" y="1092"/>
    <Point x="581" y="1092"/>
    <Point x="599" y="1024"/>
    <Point x="599" y="1024"/>
    <Point x="604" y="963"/>
    <Point x="604" y="963"/>
    <Point x="604" y="963"/>
    <Point x="604" y="963"/>
    <Point x="604" y="963"/>
    <Point x="604" y="963"/>
    <Point x="604" y="963"/>
    <Point x="634" y="1039"/>
    <Point x="657" y="1095"/>
    <Point x="685" y="1152"/>
    <Point x="720" y="1200"/>
    <Point x="759" y="1250"/>
    <Point x="802" y="1286"/>
    <Point x="848" y="1318"/>
    <Point x="894" y="1339"/>
    <Point x="945" y="1351"/>
    <Point x="999" y="1351"/>
  </Stroke>
  <Stroke>
    <Point x="645" y="1031"/>
    <Point x="649" y="982"/>
    <Point x="649" y="982"/>
    <Point x="649" y="982"/>
    <Point x="657" y="942"/>
    <Point x="657" y="942"/>
    <Point x="657" y="942"/>
    <Point x="657" y="942"/>
    <Point x="657" y="942"/>
    <Point x="607" y="908"/>
    <Point x="607" y="908"/>
    <Point x="550" y="917"/>
    <Point x="550" y="917"/>
    <Point x="483" y="951"/>
    <Point x="483" y="951"/>
    <Point x="422" y="1003"/>
    <Point x="422" y="1003"/>
    <Point x="385" y="1080"/>
    <Point x="378" y="1120"/>
    <Point x="378" y="1120"/>
    <Point x="391" y="1193"/>
    <Point x="391" y="1193"/>
    <Point x="437" y="1243"/>
    <Point x="437" y="1243"/>
    <Point x="502" y="1267"/>
    <Point x="502" y="1267"/>
    <Point x="566" y="1249"/>
    <Point x="566" y="1249"/>
    <Point x="619" y="1202"/>
    <Point x="619" y="1202"/>
    <Point x="652" y="1146"/>
    <Point x="652" y="1146"/>
    <Point x="666" y="1079"/>
    <Point x="666" y="1079"/>
    <Point x="664" y="1014"/>
    <Point x="664" y="1014"/>
    <Point x="659" y="974"/>
    <Point x="659" y="974"/>
    <Point x="659" y="974"/>
    <Point x="659" y="974"/>
    <Point x="659" y="974"/>
    <Point x="676" y="1039"/>
    <Point x="676" y="1039"/>
    <Point x="715" y="1123"/>
    <Point x="744" y="1167"/>
    <Point x="744" y="1167"/>
    <Point x="812" y="1243"/>
    <Point x="812" y="1243"/>
    <Point x="893" y="1295"/>
    <Point x="939" y="1312"/>
    <Point x="983" y="1321"/>
  </Stroke>
</StrokeSet>
