<?xml version="1.0" ?>
<StrokeSet>
  <Stroke>
    <Point x="390" y="671"/>
    <Point x="390" y="671"/>
    <Point x="381" y="672"/>
    <Point x="376" y="683"/>
    <Point x="366" y="706"/>
    <Point x="366" y="727"/>
    <Point x="360" y="768"/>
    <Point x="356" y="810"/>
    <Point x="349" y="865"/>
    <Point x="349" y="922"/>
    <Point x="347" y="979"/>
    <Point x="351" y="1032"/>
    <Point x="355" y="1078"/>
    <Point x="363" y="1111"/>
    <Point x="374" y="1132"/>
    <Point x="388" y="1135"/>
    <Point x="403" y="1123"/>
    <Point x="417" y="1096"/>
    <Point x="427" y="1055"/>
    <Point x="432" y="1005"/>
    <Point x="436" y="950"/>
    <Point x="433" y="891"/>
    <Point x="429" y="834"/>
    <Point x="425" y="780"/>
    <Point x="417" y="735"/>
    <Point x="411" y="697"/>
    <Point x="407" y="669"/>
    <Point x="410" y="650"/>
    <Point x="416" y="641"/>
    <Point x="434" y="635"/>
    <Point x="461" y="638"/>
    <Point x="496" y="642"/>
    <Point x="546" y="649"/>
    <Point x="601" y="658"/>
    <Point x="665" y="668"/>
    <Point x="733" y="684"/>
    <Point x="798" y="703"/>
    <Point x="855" y="727"/>
    <Point x="901" y="752"/>
    <Point x="935" y="784"/>
    <Point x="945" y="823"/>
    <Point x="938" y="865"/>
    <Point x="911" y="911"/>
    <Point x="868" y="957"/>
    <Point x="813" y="1002"/>
    <Point x="749" y="1043"/>
    <Point x="680" y="1076"/>
    <Point x="616" y="1103"/>
    <Point x="562" y="1119"/>
    <Point x="516" y="1129"/>
    <Point x="485" y="1132"/>
    <Point x="465" y="1132"/>
    <Point x="467" y="1120"/>
    <Point x="486" y="1113"/>
    <Point x="517" y="1108"/>
    <Point x="558" y="1103"/>
  </Stroke>
  <Stroke>
    <Point x="314" y="602"/>
    <Point x="318" y="588"/>
    <Point x="318" y="588"/>
    <Point x="308" y="582"/>
    <Point x="308" y="582"/>
    <Point x="291" y="601"/>
    <Point x="285" y="619"/>
    <Point x="272" y="655"/>
    <Point x="262" y="696"/>
    <Point x="250" y="751"/>
    <Point x="242" y="810"/>
    <Point x="235" y="875"/>
    <Point x="235" y="942"/>
    <Point x="238" y="1005"/>
    <Point x="245" y="1062"/>
    <Point x="253" y="1108"/>
    <Point x="269" y="1143"/>
    <Point x="287" y="1159"/>
    <Point x="306" y="1159"/>
    <Point x="324" y="1144"/>
    <Point x="341" y="1116"/>
    <Point x="355" y="1075"/>
    <Point x="365" y="1029"/>
    <Point x="371" y="978"/>
    <Point x="375" y="924"/>
    <Point x="373" y="870"/>
    <Point x="369" y="819"/>
    <Point x="363" y="771"/>
    <Point x="356" y="729"/>
    <Point x="350" y="695"/>
    <Point x="345" y="663"/>
    <Point x="345" y="636"/>
    <Point x="347" y="615"/>
    <Point x="353" y="599"/>
    <Point x="362" y="587"/>
    <Point x="378" y="579"/>
    <Point x="397" y="575"/>
    <Point x="423" y="573"/>
    <Point x="457" y="575"/>
    <Point x="495" y="578"/>
    <Point x="537" y="585"/>
    <Point x="580" y="594"/>
    <Point x="626" y="608"/>
    <Point x="669" y="623"/>
    <Point x="706" y="644"/>
    <Point x="733" y="671"/>
    <Point x="748" y="705"/>
    <Point x="752" y="741"/>
    <Point x="745" y="782"/>
    <Point x="724" y="825"/>
    <Point x="689" y="873"/>
    <Point x="646" y="920"/>
    <Point x="599" y="966"/>
    <Point x="551" y="1007"/>
    <Point x="504" y="1042"/>
    <Point x="462" y="1072"/>
    <Point x="427" y="1096"/>
    <Point x="404" y="1113"/>
    <Point x="387" y="1129"/>
    <Point x="388" y="1138"/>
    <Point x="402" y="1140"/>
    <Point x="424" y="1140"/>
    <Point x="454" y="1137"/>
  </Stroke>
</StrokeSet>
