<?xml version="1.0" ?>
<StrokeSet>
  <Stroke>
    <Point x="808" y="1189"/>
    <Point x="808" y="1189"/>
    <Point x="808" y="1189"/>
    <Point x="800" y="1209"/>
    <Point x="802" y="1228"/>
    <Point x="803" y="1251"/>
    <Point x="807" y="1281"/>
    <Point x="811" y="1317"/>
    <Point x="816" y="1355"/>
    <Point x="819" y="1397"/>
    <Point x="823" y="1439"/>
    <Point x="826" y="1480"/>
    <Point x="829" y="1516"/>
    <Point x="834" y="1551"/>
    <Point x="838" y="1582"/>
    <Point x="843" y="1605"/>
    <Point x="846" y="1628"/>
    <Point x="843" y="1644"/>
    <Point x="843" y="1644"/>
    <Point x="846" y="1659"/>
    <Point x="846" y="1659"/>
  </Stroke>
  <Stroke>
    <Point x="835" y="968"/>
    <Point x="835" y="968"/>
    <Point x="822" y="946"/>
    <Point x="822" y="946"/>
    <Point x="808" y="943"/>
    <Point x="808" y="943"/>
    <Point x="808" y="943"/>
    <Point x="808" y="943"/>
    <Point x="808" y="943"/>
    <Point x="808" y="943"/>
  </Stroke>
  <Stroke>
    <Point x="779" y="962"/>
    <Point x="779" y="962"/>
    <Point x="779" y="962"/>
    <Point x="779" y="962"/>
    <Point x="790" y="995"/>
    <Point x="797" y="1026"/>
    <Point x="803" y="1072"/>
    <Point x="817" y="1123"/>
    <Point x="823" y="1188"/>
    <Point x="835" y="1252"/>
    <Point x="844" y="1319"/>
    <Point x="855" y="1381"/>
    <Point x="862" y="1436"/>
    <Point x="870" y="1485"/>
    <Point x="877" y="1522"/>
    <Point x="882" y="1551"/>
    <Point x="880" y="1569"/>
    <Point x="880" y="1569"/>
    <Point x="880" y="1569"/>
    <Point x="895" y="1558"/>
  </Stroke>
  <Stroke>
    <Point x="823" y="675"/>
    <Point x="814" y="659"/>
    <Point x="816" y="634"/>
    <Point x="816" y="634"/>
    <Point x="808" y="615"/>
    <Point x="808" y="615"/>
    <Point x="808" y="615"/>
    <Point x="808" y="615"/>
    <Point x="790" y="618"/>
    <Point x="790" y="618"/>
    <Point x="790" y="618"/>
    <Point x="803" y="618"/>
  </Stroke>
</StrokeSet>
