<?xml version="1.0" ?>
<StrokeSet>
  <Stroke>
    <Point x="250" y="436"/>
    <Point x="250" y="436"/>
    <Point x="246" y="426"/>
    <Point x="246" y="415"/>
    <Point x="248" y="405"/>
    <Point x="253" y="393"/>
    <Point x="262" y="378"/>
    <Point x="273" y="361"/>
    <Point x="289" y="342"/>
    <Point x="304" y="326"/>
    <Point x="324" y="308"/>
    <Point x="346" y="294"/>
    <Point x="369" y="279"/>
    <Point x="389" y="272"/>
    <Point x="414" y="266"/>
    <Point x="436" y="264"/>
    <Point x="459" y="267"/>
    <Point x="480" y="275"/>
    <Point x="500" y="287"/>
    <Point x="516" y="306"/>
    <Point x="530" y="326"/>
    <Point x="540" y="351"/>
    <Point x="545" y="379"/>
    <Point x="544" y="413"/>
    <Point x="539" y="447"/>
    <Point x="530" y="483"/>
    <Point x="516" y="521"/>
    <Point x="499" y="559"/>
    <Point x="479" y="598"/>
    <Point x="458" y="635"/>
    <Point x="436" y="667"/>
    <Point x="415" y="699"/>
    <Point x="395" y="726"/>
    <Point x="373" y="751"/>
    <Point x="354" y="773"/>
    <Point x="339" y="790"/>
    <Point x="324" y="804"/>
    <Point x="310" y="818"/>
    <Point x="299" y="830"/>
    <Point x="291" y="839"/>
    <Point x="284" y="849"/>
    <Point x="284" y="849"/>
    <Point x="277" y="865"/>
    <Point x="274" y="876"/>
    <Point x="272" y="887"/>
    <Point x="270" y="900"/>
    <Point x="269" y="912"/>
    <Point x="267" y="929"/>
    <Point x="265" y="945"/>
    <Point x="264" y="963"/>
    <Point x="263" y="977"/>
    <Point x="262" y="993"/>
    <Point x="263" y="1003"/>
    <Point x="263" y="1003"/>
    <Point x="263" y="1017"/>
    <Point x="263" y="1017"/>
    <Point x="263" y="1017"/>
    <Point x="274" y="1007"/>
    <Point x="283" y="1000"/>
  </Stroke>
  <Stroke>
    <Point x="269" y="1318"/>
    <Point x="269" y="1318"/>
    <Point x="269" y="1318"/>
    <Point x="269" y="1318"/>
    <Point x="269" y="1318"/>
    <Point x="269" y="1318"/>
    <Point x="268" y="1307"/>
    <Point x="268" y="1307"/>
    <Point x="279" y="1300"/>
    <Point x="279" y="1300"/>
    <Point x="289" y="1291"/>
    <Point x="289" y="1291"/>
    <Point x="296" y="1282"/>
    <Point x="296" y="1282"/>
    <Point x="305" y="1267"/>
  </Stroke>
  <Stroke>
    <Point x="368" y="435"/>
    <Point x="371" y="417"/>
    <Point x="371" y="417"/>
    <Point x="381" y="398"/>
    <Point x="395" y="384"/>
    <Point x="414" y="369"/>
    <Point x="440" y="354"/>
    <Point x="467" y="342"/>
    <Point x="502" y="327"/>
    <Point x="534" y="318"/>
    <Point x="566" y="314"/>
    <Point x="591" y="315"/>
    <Point x="616" y="318"/>
    <Point x="633" y="330"/>
    <Point x="644" y="348"/>
    <Point x="648" y="374"/>
    <Point x="647" y="405"/>
    <Point x="639" y="440"/>
    <Point x="623" y="481"/>
    <Point x="605" y="527"/>
    <Point x="580" y="575"/>
    <Point x="553" y="625"/>
    <Point x="523" y="677"/>
    <Point x="491" y="729"/>
    <Point x="463" y="778"/>
    <Point x="439" y="825"/>
    <Point x="419" y="867"/>
    <Point x="401" y="908"/>
    <Point x="392" y="941"/>
    <Point x="387" y="968"/>
    <Point x="389" y="987"/>
    <Point x="396" y="1002"/>
    <Point x="405" y="1010"/>
    <Point x="423" y="1008"/>
    <Point x="446" y="1004"/>
    <Point x="461" y="999"/>
    <Point x="483" y="987"/>
    <Point x="498" y="983"/>
  </Stroke>
  <Stroke>
    <Point x="434" y="1413"/>
    <Point x="426" y="1423"/>
    <Point x="419" y="1435"/>
    <Point x="419" y="1435"/>
    <Point x="419" y="1435"/>
    <Point x="422" y="1444"/>
    <Point x="422" y="1444"/>
    <Point x="437" y="1441"/>
    <Point x="437" y="1441"/>
    <Point x="449" y="1438"/>
    <Point x="460" y="1428"/>
    <Point x="470" y="1414"/>
    <Point x="483" y="1394"/>
  </Stroke>
</StrokeSet>
